accounts/__init__.py
accounts/api/__init__.py
accounts/api/api_v1/__init__.py
accounts/api/api_v1/api.py
accounts/api/api_v1/endpoints/__init__.py
accounts/api/api_v1/endpoints/accounts.py
accounts/api/api_v1/endpoints/address.py
accounts/api/api_v1/endpoints/login.py
accounts/api/api_v1/endpoints/roles.py
accounts/api/api_v1/endpoints/user_roles.py
accounts/api/api_v1/endpoints/users.py
accounts/api/api_v1/endpoints/utils.py
accounts/api/deps.py
accounts/celeryworker_pre_start.py
accounts/constants/__init__.py
accounts/constants/role.py
accounts/core/__init__.py
accounts/core/celery_app.py
accounts/core/config.py
accounts/core/security.py
accounts/crud/__init__.py
accounts/crud/base.py
accounts/crud/crud_account.py
accounts/crud/crud_address.py
accounts/crud/crud_role.py
accounts/crud/crud_user.py
accounts/crud/crud_user_role.py
accounts/db/__init__.py
accounts/db/base.py
accounts/db/base_class.py
accounts/db/init_db.py
accounts/db/session.py
accounts/email-templates/src/new_account.mjml
accounts/email-templates/src/reset_password.mjml
accounts/email-templates/src/test_email.mjml
accounts/initial_data.py
accounts/main.py
accounts/models/__init__.py
accounts/models/account.py
accounts/models/address.py
accounts/models/role.py
accounts/models/subscription.py
accounts/models/user.py
accounts/models/user_role.py
accounts/schemas/__init__.py
accounts/schemas/account.py
accounts/schemas/address.py
accounts/schemas/item.py
accounts/schemas/msg.py
accounts/schemas/role.py
accounts/schemas/sign_up.py
accounts/schemas/token.py
accounts/schemas/user.py
accounts/schemas/user_role.py
accounts/service_pre_start.py
accounts/tests/.gitignore
accounts/tests/__init__.py
accounts/tests/api/__init__.py
accounts/tests/api/api_v1/__init__.py
accounts/tests/api/api_v1/test_celery.py
accounts/tests/api/api_v1/test_items.py
accounts/tests/api/api_v1/test_login.py
accounts/tests/api/api_v1/test_users.py
accounts/tests/conftest.py
accounts/tests/crud/__init__.py
accounts-0.2.3.dist-info/WHEEL
accounts-0.2.3.dist-info/METADATA
accounts-0.2.3.dist-info/RECORD
